searchbar_component/__init__.py
searchbar_component/example.py
searchbar_component/frontend/build/asset-manifest.json
searchbar_component/frontend/build/bootstrap.min.css
searchbar_component/frontend/build/index.html
searchbar_component/frontend/build/static/css/main.2d695fab.css
searchbar_component/frontend/build/static/css/main.2d695fab.css.map
searchbar_component/frontend/build/static/js/main.0b43c012.js
searchbar_component/frontend/build/static/js/main.0b43c012.js.LICENSE.txt
searchbar_component/frontend/build/static/js/main.0b43c012.js.map
streamlit_autosuggest-0.2.1.dist-info/LICENSE
streamlit_autosuggest-0.2.1.dist-info/METADATA
streamlit_autosuggest-0.2.1.dist-info/WHEEL
streamlit_autosuggest-0.2.1.dist-info/top_level.txt
streamlit_autosuggest-0.2.1.dist-info/RECORD
